async_pydantic_vault/__init__.py
async_pydantic_vault/settings.py
async_pydantic_vault/typing.py
async_pydantic_vault/vault_helper.py
async_pydantic_vault-0.1.15.dist-info/WHEEL
async_pydantic_vault-0.1.15.dist-info/METADATA
async_pydantic_vault-0.1.15.dist-info/RECORD
